MANIFEST.in
README.md
setup.cfg
setup.py
versioneer.py
basis_set_exchange/__init__.py
basis_set_exchange/_version.py
basis_set_exchange/api.py
basis_set_exchange/bundle.py
basis_set_exchange/compose.py
basis_set_exchange/conftest.py
basis_set_exchange/fileio.py
basis_set_exchange/lut.py
basis_set_exchange/manip.py
basis_set_exchange/memo.py
basis_set_exchange/misc.py
basis_set_exchange/notes.py
basis_set_exchange/printing.py
basis_set_exchange/references.py
basis_set_exchange/sort.py
basis_set_exchange/validator.py
basis_set_exchange.egg-info/PKG-INFO
basis_set_exchange.egg-info/SOURCES.txt
basis_set_exchange.egg-info/dependency_links.txt
basis_set_exchange.egg-info/entry_points.txt
basis_set_exchange.egg-info/requires.txt
basis_set_exchange.egg-info/top_level.txt
basis_set_exchange.egg-info/zip-safe
basis_set_exchange/cli/__init__.py
basis_set_exchange/cli/bse_cli.py
basis_set_exchange/cli/bse_handlers.py
basis_set_exchange/cli/bsecurate_cli.py
basis_set_exchange/cli/bsecurate_handlers.py
basis_set_exchange/cli/check.py
basis_set_exchange/cli/common.py
basis_set_exchange/cli/complete.py
basis_set_exchange/converters/__init__.py
basis_set_exchange/converters/bsedebug.py
basis_set_exchange/converters/bsejson.py
basis_set_exchange/converters/cfour.py
basis_set_exchange/converters/common.py
basis_set_exchange/converters/convert.py
basis_set_exchange/converters/cp2k.py
basis_set_exchange/converters/dalton.py
basis_set_exchange/converters/demon2k.py
basis_set_exchange/converters/g94.py
basis_set_exchange/converters/gamess_uk.py
basis_set_exchange/converters/gamess_us.py
basis_set_exchange/converters/molcas.py
basis_set_exchange/converters/molpro.py
basis_set_exchange/converters/nwchem.py
basis_set_exchange/converters/psi4.py
basis_set_exchange/converters/qchem.py
basis_set_exchange/converters/qcschema.py
basis_set_exchange/converters/turbomole.py
basis_set_exchange/curate/__init__.py
basis_set_exchange/curate/add_basis.py
basis_set_exchange/curate/compare.py
basis_set_exchange/curate/compare_report.py
basis_set_exchange/curate/diff.py
basis_set_exchange/curate/graph.py
basis_set_exchange/curate/metadata.py
basis_set_exchange/curate/misc.py
basis_set_exchange/curate/skel.py
basis_set_exchange/curate/readers/__init__.py
