Metadata-Version: 2.1
Name: basis-set-exchange
Version: 0.8.9
Summary: The Quantum Chemistry Basis Set Exchange
Home-page: https://github.com/MolSSI-BSE/basis_set_exchange
Author: The Molecular Sciences Software Institute
Author-email: bpp4@vt.edu
License: BSD-3C
Platform: UNKNOWN
Classifier: Development Status :: 4 - Beta
Classifier: Intended Audience :: Science/Research
Classifier: Programming Language :: Python :: 3
Classifier: Programming Language :: Python :: 3.5
Classifier: Programming Language :: Python :: 3.6
Classifier: Programming Language :: Python :: 3.7
Requires-Python: >=3
Provides-Extra: tests
Provides-Extra: curate
Provides-Extra: docs
